vdoc/__init__.py
vdoc/constants.py
vdoc/py.typed
vdoc/api/__init__.py
vdoc/api/lifespan.py
vdoc/api/dependencies/__init__.py
vdoc/api/dependencies/auth.py
vdoc/api/routes/__init__.py
vdoc/api/routes/plugins.py
vdoc/api/routes/project_categories.py
vdoc/api/routes/projects.py
vdoc/api/routes/version.py
vdoc/cli/__init__.py
vdoc/cli/main.py
vdoc/cli/run.py
vdoc/docs/configuration.html
vdoc/docs/development.html
vdoc/docs/genindex.html
vdoc/docs/getting_started.html
vdoc/docs/index.html
vdoc/docs/license_compliance.html
vdoc/docs/objects.inv
vdoc/docs/plugins.html
vdoc/docs/py-modindex.html
vdoc/docs/search.html
vdoc/docs/searchindex.js
vdoc/docs/vdoc.api.dependencies.html
vdoc/docs/vdoc.api.html
vdoc/docs/vdoc.api.routes.html
vdoc/docs/vdoc.cli.html
vdoc/docs/vdoc.exceptions.html
vdoc/docs/vdoc.html
vdoc/docs/vdoc.methods.api.html
vdoc/docs/vdoc.methods.cli.html
vdoc/docs/vdoc.methods.html
vdoc/docs/vdoc.models.html
vdoc/docs/vdoc.models.plugins.html
vdoc/docs/vdoc.settings.html
vdoc/docs/_sources/configuration.rst.txt
vdoc/docs/_sources/development.rst.txt
vdoc/docs/_sources/getting_started.rst.txt
vdoc/docs/_sources/index.rst.txt
vdoc/docs/_sources/license_compliance.rst.txt
vdoc/docs/_sources/plugins.rst.txt
vdoc/docs/_sources/vdoc.api.dependencies.rst.txt
vdoc/docs/_sources/vdoc.api.routes.rst.txt
vdoc/docs/_sources/vdoc.api.rst.txt
vdoc/docs/_sources/vdoc.cli.rst.txt
vdoc/docs/_sources/vdoc.exceptions.rst.txt
vdoc/docs/_sources/vdoc.methods.api.rst.txt
vdoc/docs/_sources/vdoc.methods.cli.rst.txt
vdoc/docs/_sources/vdoc.methods.rst.txt
vdoc/docs/_sources/vdoc.models.plugins.rst.txt
vdoc/docs/_sources/vdoc.models.rst.txt
vdoc/docs/_sources/vdoc.rst.txt
vdoc/docs/_sources/vdoc.settings.rst.txt
vdoc/docs/_sources/plugins/footer.rst.txt
vdoc/docs/_sources/plugins/theme.rst.txt
vdoc/docs/_static/0fc70aa4dfe4d16d7073.woff
vdoc/docs/_static/583e3f428bf2362b546d.woff
vdoc/docs/_static/5be6ec379613f10aea3f.woff
vdoc/docs/_static/76c1862325ea6f70eeff.woff2
vdoc-0.20.0.dist-info/licenses/LICENSE.txt
vdoc-0.20.0.dist-info/METADATA
vdoc-0.20.0.dist-info/WHEEL
vdoc-0.20.0.dist-info/entry_points.txt
vdoc-0.20.0.dist-info/top_level.txt
vdoc-0.20.0.dist-info/RECORD
