Metadata-Version: 2.4
Name: vdoc
Version: 0.20.0
Summary: Multi version documentation hosting.
Home-page: https://github.com/vorausrobotik/vdoc
Author: Jan-Frederik Schmidt
Author-email: jan-frederik.schmidt@vorausrobotik.com
License: MIT
Classifier: Programming Language :: Python
Classifier: Programming Language :: Python :: 3
Classifier: Programming Language :: Python :: 3 :: Only
Classifier: Programming Language :: Python :: 3.11
Classifier: Programming Language :: Python :: 3.12
Classifier: Programming Language :: Python :: 3.13
Classifier: License :: OSI Approved :: MIT License
Classifier: Operating System :: MacOS :: MacOS X
Classifier: Operating System :: POSIX :: Linux
Classifier: Natural Language :: English
Requires-Python: >=3.11
License-File: LICENSE.txt
Requires-Dist: importlib-metadata
Requires-Dist: packaging
Requires-Dist: fastapi
Requires-Dist: python-multipart
Requires-Dist: typer
Requires-Dist: rich
Requires-Dist: uvicorn
Requires-Dist: pydantic~=2.0
Requires-Dist: pydantic-settings~=2.0
Provides-Extra: dev
Requires-Dist: tox==4.24.1; extra == "dev"
Requires-Dist: tox-uv==1.23.0; extra == "dev"
Requires-Dist: isort==6.0.0; extra == "dev"
Requires-Dist: black==25.1.0; extra == "dev"
Requires-Dist: mypy==1.15.0; extra == "dev"
Requires-Dist: pylint==3.3.4; extra == "dev"
Requires-Dist: pytest==8.3.4; extra == "dev"
Requires-Dist: types-docutils; extra == "dev"
Requires-Dist: types-setuptools; extra == "dev"
Requires-Dist: jinja2==3.1.5; extra == "dev"
Requires-Dist: ruff==0.9.5; extra == "dev"
Requires-Dist: httpx; extra == "dev"
Requires-Dist: tenacity; extra == "dev"
Requires-Dist: requests; extra == "dev"
Requires-Dist: types-requests; extra == "dev"
Requires-Dist: pytest==8.3.4; extra == "dev"
Requires-Dist: pytest-randomly==3.16.0; extra == "dev"
Requires-Dist: pytest-cov==6.0.0; extra == "dev"
Requires-Dist: coverage[toml]==7.6.11; extra == "dev"
Requires-Dist: httpx; extra == "dev"
Requires-Dist: sphinx; extra == "dev"
Requires-Dist: tenacity; extra == "dev"
Requires-Dist: requests; extra == "dev"
Requires-Dist: sphinxawesome-theme; extra == "dev"
Requires-Dist: sphinx==8.1.3; extra == "dev"
Requires-Dist: sphinxawesome-theme==5.3.2; extra == "dev"
Requires-Dist: sphinx-selective-exclude==1.0.3; extra == "dev"
Requires-Dist: sphinx-autodoc-typehints==3.0.1; extra == "dev"
Requires-Dist: pip-licenses==5.0.0; extra == "dev"
Requires-Dist: jinja2==3.1.5; extra == "dev"
Requires-Dist: doc8==1.1.2; extra == "dev"
Requires-Dist: build[virtualenv]==1.2.2.post1; extra == "dev"
Provides-Extra: lint
Requires-Dist: isort==6.0.0; extra == "lint"
Requires-Dist: black==25.1.0; extra == "lint"
Requires-Dist: mypy==1.15.0; extra == "lint"
Requires-Dist: pylint==3.3.4; extra == "lint"
Requires-Dist: pytest==8.3.4; extra == "lint"
Requires-Dist: types-docutils; extra == "lint"
Requires-Dist: types-setuptools; extra == "lint"
Requires-Dist: jinja2==3.1.5; extra == "lint"
Requires-Dist: ruff==0.9.5; extra == "lint"
Requires-Dist: httpx; extra == "lint"
Requires-Dist: tenacity; extra == "lint"
Requires-Dist: requests; extra == "lint"
Requires-Dist: types-requests; extra == "lint"
Provides-Extra: test
Requires-Dist: pytest==8.3.4; extra == "test"
Requires-Dist: pytest-randomly==3.16.0; extra == "test"
Requires-Dist: pytest-cov==6.0.0; extra == "test"
Requires-Dist: coverage[toml]==7.6.11; extra == "test"
Requires-Dist: httpx; extra == "test"
Requires-Dist: sphinx; extra == "test"
Requires-Dist: tenacity; extra == "test"
Requires-Dist: requests; extra == "test"
Requires-Dist: sphinxawesome-theme; extra == "test"
Provides-Extra: doc
Requires-Dist: sphinx==8.1.3; extra == "doc"
Requires-Dist: sphinxawesome-theme==5.3.2; extra == "doc"
Requires-Dist: sphinx-selective-exclude==1.0.3; extra == "doc"
Requires-Dist: sphinx-autodoc-typehints==3.0.1; extra == "doc"
Requires-Dist: pip-licenses==5.0.0; extra == "doc"
Requires-Dist: jinja2==3.1.5; extra == "doc"
Requires-Dist: doc8==1.1.2; extra == "doc"
Provides-Extra: build
Requires-Dist: build[virtualenv]==1.2.2.post1; extra == "build"
Provides-Extra: tox
Requires-Dist: tox==4.24.1; extra == "tox"
Requires-Dist: tox-uv==1.23.0; extra == "tox"
Provides-Extra: lint-template
Requires-Dist: isort==6.0.0; extra == "lint-template"
Requires-Dist: black==25.1.0; extra == "lint-template"
Requires-Dist: mypy==1.15.0; extra == "lint-template"
Requires-Dist: pylint==3.3.4; extra == "lint-template"
Requires-Dist: pytest==8.3.4; extra == "lint-template"
Requires-Dist: types-docutils; extra == "lint-template"
Requires-Dist: types-setuptools; extra == "lint-template"
Requires-Dist: jinja2==3.1.5; extra == "lint-template"
Requires-Dist: ruff==0.9.5; extra == "lint-template"
Provides-Extra: test-template
Requires-Dist: pytest==8.3.4; extra == "test-template"
Requires-Dist: pytest-randomly==3.16.0; extra == "test-template"
Requires-Dist: pytest-cov==6.0.0; extra == "test-template"
Requires-Dist: coverage[toml]==7.6.11; extra == "test-template"
Provides-Extra: doc-template
Requires-Dist: sphinx==8.1.3; extra == "doc-template"
Requires-Dist: sphinxawesome-theme==5.3.2; extra == "doc-template"
Requires-Dist: sphinx-selective-exclude==1.0.3; extra == "doc-template"
Requires-Dist: sphinx-autodoc-typehints==3.0.1; extra == "doc-template"
Requires-Dist: pip-licenses==5.0.0; extra == "doc-template"
Requires-Dist: jinja2==3.1.5; extra == "doc-template"
Requires-Dist: doc8==1.1.2; extra == "doc-template"
Provides-Extra: build-template
Requires-Dist: build[virtualenv]==1.2.2.post1; extra == "build-template"
Dynamic: license-file
